{
  "_format": "hh-sol-cache-2",
  "files": {
    "/Users/tomasmehdi/solidity/solidity/hardhat/contracts/AdminBox.sol": {
      "lastModificationDate": 1661463054058,
      "contentHash": "d1de5964b0f15ec1dc7b9a85e8d0c482",
      "sourceName": "contracts/AdminBox.sol",
      "solcConfig": {
        "version": "0.8.9",
        "settings": {
          "optimizer": {
            "enabled": false,
            "runs": 200
          },
          "outputSelection": {
            "*": {
              "*": [
                "abi",
                "evm.bytecode",
                "evm.deployedBytecode",
                "evm.methodIdentifiers",
                "metadata",
                "storageLayout"
              ],
              "": [
                "ast"
              ]
            }
          }
        }
      },
      "imports": [
        "@openzeppelin/contracts-upgradeable/proxy/utils/Initializable.sol"
      ],
      "versionPragmas": [
        "^0.8.0"
      ],
      "artifacts": [
        "AdminBox"
      ]
    },
    "/Users/tomasmehdi/solidity/solidity/hardhat/node_modules/@openzeppelin/contracts-upgradeable/proxy/utils/Initializable.sol": {
      "lastModificationDate": 1661462413293,
      "contentHash": "b98e2f3a856e6e7f2106fb919bacab9e",
      "sourceName": "@openzeppelin/contracts-upgradeable/proxy/utils/Initializable.sol",
      "solcConfig": {
        "version": "0.8.9",
        "settings": {
          "optimizer": {
            "enabled": false,
            "runs": 200
          },
          "outputSelection": {
            "*": {
              "*": [
                "abi",
                "evm.bytecode",
                "evm.deployedBytecode",
                "evm.methodIdentifiers",
                "metadata",
                "storageLayout"
              ],
              "": [
                "ast"
              ]
            }
          }
        }
      },
      "imports": [
        "../../utils/AddressUpgradeable.sol"
      ],
      "versionPragmas": [
        "^0.8.2"
      ],
      "artifacts": [
        "Initializable"
      ]
    },
    "/Users/tomasmehdi/solidity/solidity/hardhat/node_modules/@openzeppelin/contracts-upgradeable/utils/AddressUpgradeable.sol": {
      "lastModificationDate": 1661462413254,
      "contentHash": "d42e87f4fba2b03ab4d3c14cb53d0c51",
      "sourceName": "@openzeppelin/contracts-upgradeable/utils/AddressUpgradeable.sol",
      "solcConfig": {
        "version": "0.8.9",
        "settings": {
          "optimizer": {
            "enabled": false,
            "runs": 200
          },
          "outputSelection": {
            "*": {
              "*": [
                "abi",
                "evm.bytecode",
                "evm.deployedBytecode",
                "evm.methodIdentifiers",
                "metadata",
                "storageLayout"
              ],
              "": [
                "ast"
              ]
            }
          }
        }
      },
      "imports": [],
      "versionPragmas": [
        "^0.8.1"
      ],
      "artifacts": [
        "AddressUpgradeable"
      ]
    },
    "/Users/tomasmehdi/solidity/solidity/hardhat/contracts/Box.sol": {
      "lastModificationDate": 1661462654005,
      "contentHash": "7952da6fb5550663741484d7a2c9f0ce",
      "sourceName": "contracts/Box.sol",
      "solcConfig": {
        "version": "0.8.9",
        "settings": {
          "optimizer": {
            "enabled": false,
            "runs": 200
          },
          "outputSelection": {
            "*": {
              "*": [
                "abi",
                "evm.bytecode",
                "evm.deployedBytecode",
                "evm.methodIdentifiers",
                "metadata",
                "storageLayout"
              ],
              "": [
                "ast"
              ]
            }
          }
        }
      },
      "imports": [],
      "versionPragmas": [
        "^0.8.0"
      ],
      "artifacts": [
        "Box"
      ]
    },
    "/Users/tomasmehdi/solidity/solidity/hardhat/contracts/BoxV2.sol": {
      "lastModificationDate": 1661462060565,
      "contentHash": "d7ba095c4f0a0fa648ba0e47020f0e32",
      "sourceName": "contracts/BoxV2.sol",
      "solcConfig": {
        "version": "0.8.9",
        "settings": {
          "optimizer": {
            "enabled": false,
            "runs": 200
          },
          "outputSelection": {
            "*": {
              "*": [
                "abi",
                "evm.bytecode",
                "evm.deployedBytecode",
                "evm.methodIdentifiers",
                "metadata",
                "storageLayout"
              ],
              "": [
                "ast"
              ]
            }
          }
        }
      },
      "imports": [],
      "versionPragmas": [
        "^0.8.0"
      ],
      "artifacts": [
        "BoxV2"
      ]
    }
  }
}
